botocore-stubs/__init__.pyi
botocore-stubs/args.pyi
botocore-stubs/auth.pyi
botocore-stubs/awsrequest.pyi
botocore-stubs/client.pyi
botocore-stubs/compat.pyi
botocore-stubs/config.pyi
botocore-stubs/configloader.pyi
botocore-stubs/configprovider.pyi
botocore-stubs/credentials.pyi
botocore-stubs/discovery.pyi
botocore-stubs/endpoint.pyi
botocore-stubs/errorfactory.pyi
botocore-stubs/eventstream.pyi
botocore-stubs/exceptions.pyi
botocore-stubs/handlers.pyi
botocore-stubs/history.pyi
botocore-stubs/hooks.pyi
botocore-stubs/httpsession.pyi
botocore-stubs/loaders.pyi
botocore-stubs/model.pyi
botocore-stubs/monitoring.pyi
botocore-stubs/paginate.pyi
botocore-stubs/parsers.pyi
botocore-stubs/regions.pyi
botocore-stubs/response.pyi
botocore-stubs/retries/__init__.pyi
botocore-stubs/retries/adaptive.pyi
botocore-stubs/retries/base.pyi
botocore-stubs/retries/bucket.pyi
botocore-stubs/retries/quota.pyi
botocore-stubs/retries/special.pyi
botocore-stubs/retries/standard.pyi
botocore-stubs/retries/throttling.pyi
botocore-stubs/retryhandler.pyi
botocore-stubs/serialize.pyi
botocore-stubs/session.pyi
botocore-stubs/signers.pyi
botocore-stubs/stub.pyi
botocore-stubs/translate.pyi
botocore-stubs/utils.pyi
botocore-stubs/validate.pyi
botocore-stubs/waiter.pyi
botocore_types-0.2.2.dist-info/WHEEL
botocore_types-0.2.2.dist-info/METADATA
botocore_types-0.2.2.dist-info/RECORD
