Metadata-Version: 2.1
Name: botocore-types
Version: 0.2.2
Summary: Type stubs for botocore
Home-page: https://github.com/sbdchd/botocore-types
License: Apache-2.0
Keywords: botocore,boto,types,mypy,stubs
Author: Steve Dignam
Author-email: steve@dignam.xyz
Requires-Python: >=3.7,<4.0
Classifier: License :: OSI Approved :: Apache Software License
Classifier: Programming Language :: Python :: 3
Classifier: Programming Language :: Python :: 3.7
Project-URL: Repository, https://github.com/sbdchd/botocore-types
